{
    "FailingTestCase": "26", 
    "FailingTestCaseExecution": "2014", 
    "InmutatedGen": "8839", 
    "NotAppliedOp": "0", 
    "OfAppliedOp": "8971", 
    "RegressionTestCases": "0", 
    "RegressionTestExecution": "0", 
    "RightCompilation": "2013", 
    "WrongCompilation": "6958", 
    "date": "Tue Aug 25 01:23:07 CEST 2015\n\n", 
    "gen": "8971", 
    "gens": "60", 
    "node": "griffon-62.nancy.grid5000.fr", 
    "operations": [], 
    "ops": "0", 
    "patches": "0", 
    "programVariant": null, 
    "timeEvaluation": "3660091", 
    "timeTotal": "4038981", 
    "unfinishValidation": "0"
}